csv_editor/__init__.py
csv_editor/server.py
csv_editor/models/__init__.py
csv_editor/models/auto_save.py
csv_editor/models/csv_session.py
csv_editor/models/data_models.py
csv_editor/models/history_manager.py
csv_editor/prompts/__init__.py
csv_editor/prompts/data_prompts.py
csv_editor/resources/__init__.py
csv_editor/resources/csv_resources.py
csv_editor/tools/__init__.py
csv_editor/tools/analytics.py
csv_editor/tools/auto_save_operations.py
csv_editor/tools/data_operations.py
csv_editor/tools/history_operations.py
csv_editor/tools/io_operations.py
csv_editor/tools/transformations.py
csv_editor/tools/validation.py
csv_editor/utils/__init__.py
csv_editor/utils/validators.py
csv_mcp_server-1.0.0.dist-info/METADATA
csv_mcp_server-1.0.0.dist-info/WHEEL
csv_mcp_server-1.0.0.dist-info/entry_points.txt
csv_mcp_server-1.0.0.dist-info/licenses/LICENSE
csv_mcp_server-1.0.0.dist-info/RECORD
