Metadata-Version: 2.4
Name: csv-mcp-server
Version: 1.0.0
Summary: MCP server for comprehensive CSV file operations with pandas-based tools
Project-URL: Homepage, https://github.com/santoshray02/csv-editor
Project-URL: Documentation, https://github.com/santoshray02/csv-editor#readme
Project-URL: Repository, https://github.com/santoshray02/csv-editor
Project-URL: Issues, https://github.com/santoshray02/csv-editor/issues
Project-URL: Changelog, https://github.com/santoshray02/csv-editor/blob/main/CHANGELOG.md
Project-URL: Release Notes, https://github.com/santoshray02/csv-editor/releases
Author-email: Santosh Ray <rayskumar02@gmail.com>
Maintainer-email: Santosh Ray <rayskumar02@gmail.com>
License: MIT
License-File: LICENSE
Keywords: csv,data-analysis,data-manipulation,data-profiling,data-quality,data-validation,fastmcp,mcp,model-context-protocol,outlier-detection,pandas
Classifier: Development Status :: 4 - Beta
Classifier: Framework :: AsyncIO
Classifier: Intended Audience :: Developers
Classifier: Intended Audience :: Financial and Insurance Industry
Classifier: Intended Audience :: Science/Research
Classifier: License :: OSI Approved :: MIT License
Classifier: Operating System :: OS Independent
Classifier: Programming Language :: Python
Classifier: Programming Language :: Python :: 3
Classifier: Programming Language :: Python :: 3.8
Classifier: Programming Language :: Python :: 3.9
Classifier: Programming Language :: Python :: 3.10
Classifier: Programming Language :: Python :: 3.11
Classifier: Programming Language :: Python :: 3.12
Classifier: Programming Language :: Python :: 3.13
Classifier: Topic :: Office/Business :: Financial :: Spreadsheet
Classifier: Topic :: Scientific/Engineering :: Information Analysis
Classifier: Topic :: Software Development :: Libraries :: Python Modules
Classifier: Topic :: Utilities
Classifier: Typing :: Typed
Requires-Python: >=3.10
Requires-Dist: aiofiles>=24.1.0
Requires-Dist: fastmcp>=2.11.3
Requires-Dist: httpx>=0.27.0
Requires-Dist: numpy>=2.1.3
Requires-Dist: openpyxl>=3.1.5
Requires-Dist: pandas>=2.2.3
Requires-Dist: pyarrow>=17.0.0
Requires-Dist: pydantic>=2.10.4
Requires-Dist: python-dateutil>=2.9.0
Requires-Dist: pytz>=2024.2
Requires-Dist: tabulate>=0.9.0
Provides-Extra: all
Requires-Dist: black>=24.10.0; extra == 'all'
Requires-Dist: bottleneck>=1.4.0; extra == 'all'
Requires-Dist: faker>=30.0.0; extra == 'all'
Requires-Dist: fastparquet>=2024.11.0; extra == 'all'
Requires-Dist: hypothesis>=6.122.0; extra == 'all'
Requires-Dist: ipython>=8.29.0; extra == 'all'
Requires-Dist: mkdocs-material>=9.5.0; extra == 'all'
Requires-Dist: mkdocs-mermaid2-plugin>=1.1.0; extra == 'all'
Requires-Dist: mkdocs>=1.6.0; extra == 'all'
Requires-Dist: mkdocstrings[python]>=0.26.0; extra == 'all'
Requires-Dist: mypy>=1.13.0; extra == 'all'
Requires-Dist: numexpr>=2.10.0; extra == 'all'
Requires-Dist: pandas-stubs>=2.2.3; extra == 'all'
Requires-Dist: pre-commit>=4.0.0; extra == 'all'
Requires-Dist: pytest-asyncio>=0.24.0; extra == 'all'
Requires-Dist: pytest-benchmark>=5.0.0; extra == 'all'
Requires-Dist: pytest-cov>=5.0.0; extra == 'all'
Requires-Dist: pytest-mock>=3.14.0; extra == 'all'
Requires-Dist: pytest>=8.3.0; extra == 'all'
Requires-Dist: rich>=13.9.0; extra == 'all'
Requires-Dist: ruff>=0.7.0; extra == 'all'
Requires-Dist: types-aiofiles>=24.1.0; extra == 'all'
Requires-Dist: types-pytz>=2024.2; extra == 'all'
Requires-Dist: types-tabulate>=0.9.0; extra == 'all'
Provides-Extra: dev
Requires-Dist: black>=24.10.0; extra == 'dev'
Requires-Dist: ipython>=8.29.0; extra == 'dev'
Requires-Dist: mypy>=1.13.0; extra == 'dev'
Requires-Dist: pandas-stubs>=2.2.3; extra == 'dev'
Requires-Dist: pre-commit>=4.0.0; extra == 'dev'
Requires-Dist: pytest-asyncio>=0.24.0; extra == 'dev'
Requires-Dist: pytest-benchmark>=5.0.0; extra == 'dev'
Requires-Dist: pytest-cov>=5.0.0; extra == 'dev'
Requires-Dist: pytest-mock>=3.14.0; extra == 'dev'
Requires-Dist: pytest>=8.3.0; extra == 'dev'
Requires-Dist: rich>=13.9.0; extra == 'dev'
Requires-Dist: ruff>=0.7.0; extra == 'dev'
Requires-Dist: types-aiofiles>=24.1.0; extra == 'dev'
Requires-Dist: types-pytz>=2024.2; extra == 'dev'
Requires-Dist: types-tabulate>=0.9.0; extra == 'dev'
Provides-Extra: docs
Requires-Dist: mkdocs-material>=9.5.0; extra == 'docs'
Requires-Dist: mkdocs-mermaid2-plugin>=1.1.0; extra == 'docs'
Requires-Dist: mkdocs>=1.6.0; extra == 'docs'
Requires-Dist: mkdocstrings[python]>=0.26.0; extra == 'docs'
Provides-Extra: performance
Requires-Dist: bottleneck>=1.4.0; extra == 'performance'
Requires-Dist: fastparquet>=2024.11.0; extra == 'performance'
Requires-Dist: numexpr>=2.10.0; extra == 'performance'
Provides-Extra: test
Requires-Dist: faker>=30.0.0; extra == 'test'
Requires-Dist: hypothesis>=6.122.0; extra == 'test'
Requires-Dist: pytest-asyncio>=0.24.0; extra == 'test'
Requires-Dist: pytest-benchmark>=5.0.0; extra == 'test'
Requires-Dist: pytest-cov>=5.0.0; extra == 'test'
Requires-Dist: pytest-mock>=3.14.0; extra == 'test'
Requires-Dist: pytest>=8.3.0; extra == 'test'
